panoptic_parts/__init__.py
panoptic_parts/cityscapes_panoptic_parts/__init__.py
panoptic_parts/evaluation/__init__.py
panoptic_parts/evaluation/eval_PartPQ.py
panoptic_parts/evaluation/experimental_eval_PartIOU.py
panoptic_parts/evaluation/prepare_data.py
panoptic_parts/merging/__init__.py
panoptic_parts/merging/merge_to_panoptic.py
panoptic_parts/merging/merge_to_pps.py
panoptic_parts/pascal_panoptic_parts/__init__.py
panoptic_parts/specs/__init__.py
panoptic_parts/specs/dataset_spec.py
panoptic_parts/specs/eval_spec.py
panoptic_parts/specs/dataset_specs/cpp_datasetspec.yaml
panoptic_parts/specs/dataset_specs/ppp_datasetspec.yaml
panoptic_parts/specs/eval_specs/ppq_cpp_19_23_cvpr21_default_evalspec.yaml
panoptic_parts/specs/eval_specs/ppq_cpp_19_23_cvpr21_grouped_evalspec.yaml
panoptic_parts/specs/eval_specs/ppq_ppp_59_57_cvpr21_default_evalspec.yaml
panoptic_parts/utils/__init__.py
panoptic_parts/utils/evaluation_PartPQ.py
panoptic_parts/utils/experimental_evaluation_IOU.py
panoptic_parts/utils/format.py
panoptic_parts/utils/utils.py
panoptic_parts/utils/visualization.py
panoptic_parts/visualization/__init__.py
panoptic_parts/visualization/visualize_label_with_legend.py
panoptic_parts-2.0rc6.dist-info/LICENSE
panoptic_parts-2.0rc6.dist-info/METADATA
panoptic_parts-2.0rc6.dist-info/WHEEL
panoptic_parts-2.0rc6.dist-info/entry_points.txt
panoptic_parts-2.0rc6.dist-info/top_level.txt
panoptic_parts-2.0rc6.dist-info/RECORD
