Metadata-Version: 2.1
Name: panoptic-parts
Version: 2.0rc6
Summary: Panoptic Parts datasets
Home-page: https://github.com/pmeletis/panoptic_parts
Author: Panoptic Parts team
Author-email: panoptic.parts@outlook.com
Maintainer: Panagiotis Meletis
Maintainer-email: panoptic.parts@outlook.com
License: UNKNOWN
Project-URL: Documentation, https://panoptic-parts.readthedocs.io
Project-URL: Bug Tracker, https://github.com/pmeletis/panoptic_parts/issues
Platform: UNKNOWN
Classifier: Programming Language :: Python :: 3
Classifier: Programming Language :: Python :: 3.7
Classifier: Operating System :: OS Independent
Requires-Python: >=3.7
License-File: LICENSE
Requires-Dist: numpy (>=1.15)
Requires-Dist: Pillow (>=8.0)
Requires-Dist: scipy (>=1.4)
Requires-Dist: ruamel.yaml (>=0.15)
Requires-Dist: matplotlib (>=3.3.0)
Provides-Extra: merging
Requires-Dist: tqdm ; extra == 'merging'
Requires-Dist: pycocotools (>=2.0.0) ; extra == 'merging'
